<?xml version="1.0" encoding="UTF-8"?>
<!DOCTYPE suite SYSTEM "http://testng.org/testng-1.0.dtd">

<suite name="Test-Suite">
    <test name="Local Browser">
        <!--below cloud property is used for distinguish desired capabilities between cloud and local-->
        <!--and also to choose between RemoteWebDriver and WebDriver if "OnlineOrMobile" is "Online"-->
        <parameter name="Cloud" value="false"/>
        <parameter name="browser" value="Chrome"/>
        <parameter name="platform" value="Windows"/>
        <parameter name="platformVersion" value="11"/>
        <parameter name="username" value="abc@gmail.com"/>
        <parameter name="password" value="password@123"/>
        <!--below OnlineOrMobile parameter is used to decide whether-->
        <!--AppiumDriver or RemoteWebDriver should be instantiated-->
        <parameter name="OnlineOrMobile" value="OnlineLocal"/>
        <classes>
            <class name="cucumber.testRunners.TestNGSequentialRunnerOnline"/>
        </classes>
    </test>
</suite>